nifigen/__init__.py
nifigen/agutils.py
nifigen/nifigen.py
nifigen-0.14.0.dist-info/licenses/LICENSE
nifigen-0.14.0.dist-info/METADATA
nifigen-0.14.0.dist-info/WHEEL
nifigen-0.14.0.dist-info/top_level.txt
nifigen-0.14.0.dist-info/RECORD
