Metadata-Version: 2.4
Name: nifigen
Version: 0.14.0
Summary: nifigen
Author: nifigen
License: MIT
Classifier: Programming Language :: Python :: 3
Classifier: License :: OSI Approved :: MIT License
Classifier: Operating System :: OS Independent
Requires-Python: >=3.11
License-File: LICENSE
Dynamic: license-file
